kuqueue/__init__.py
kuqueue/kuqueue.py
kuqueue-0.1.2.dist-info/WHEEL
kuqueue-0.1.2.dist-info/METADATA
kuqueue-0.1.2.dist-info/RECORD
