Metadata-Version: 2.1
Name: kuqueue
Version: 0.1.2
Summary: An easy pythonic redis-based MQ
Home-page: https://github.com/yehonatanz/kuqueue
License: MIT
Keywords: rsmq,mq,queue,redis,kuqueue
Author: Yehonatan Zecharia
Author-email: yonti95@gmail.com
Requires-Python: >=3.8,<4.0
Classifier: License :: OSI Approved :: MIT License
Classifier: Programming Language :: Python :: 3
Classifier: Programming Language :: Python :: 3.8
Classifier: Programming Language :: Python :: 3.9
Classifier: Topic :: System :: Distributed Computing
Requires-Dist: pyrsmq (>=0.4.3,<0.5.0)
Requires-Dist: redis (>=3.5.3,<4.0.0)
Project-URL: Repository, https://github.com/yehonatanz/kuqueue
